<?xml version="1.0" encoding="UTF-8"?>
<con:soapui-project id="ce5b5b51-b2a0-4fe8-8c1a-37392b167812" activeEnvironment="Default" name="REST Project 1" soapui-version="5.6.0" xmlns:con="http://eviware.com/soapui/config"><con:settings/><con:interface xsi:type="con:RestService" id="e1592512-5afd-4d65-b605-7449a9833edb" wadlVersion="http://wadl.dev.java.net/2009/02" name="http://localhost:8080" type="rest" xmlns:xsi="http://www.w3.org/2001/XMLSchema-instance"><con:settings/><con:definitionCache/><con:endpoints><con:endpoint>http://localhost:8080</con:endpoint></con:endpoints><con:resource name="Greeting" path="/greeting" id="299c3f6f-8d1e-4ad4-a332-3bf85ba144e2"><con:settings/><con:parameters><con:parameter><con:name>name</con:name><con:value>"bob"</con:value><con:style>QUERY</con:style><con:default>"bob"</con:default><con:path xsi:nil="true"/><con:description xsi:nil="true"/></con:parameter></con:parameters><con:method name="Greeting 1" id="5cbb55bc-724d-42ba-89cb-c6383167ba93" method="GET"><con:settings/><con:parameters/><con:representation type="RESPONSE"><con:mediaType>text/plain;charset=UTF-8</con:mediaType><con:status>200</con:status><con:params/><con:element>data</con:element></con:representation><con:request name="Request 1" id="8ee6ba9c-521e-4189-9cb6-515a193b7595" mediaType="application/json"><con:settings><con:setting id="com.eviware.soapui.impl.wsdl.WsdlRequest@request-headers">&lt;xml-fragment/></con:setting></con:settings><con:endpoint>http://localhost:8080</con:endpoint><con:request/><con:originalUri>http://localhost/greeting</con:originalUri><con:credentials><con:authType>No Authorization</con:authType></con:credentials><con:jmsConfig JMSDeliveryMode="PERSISTENT"/><con:jmsPropertyConfig/><con:parameters><entry key="name" value="Alice" xmlns="http://eviware.com/soapui/config"/></con:parameters><con:parameterOrder><con:entry>name</con:entry></con:parameterOrder></con:request></con:method></con:resource><con:resource name="users" path="/user/addUser" id="ad8dabf8-b04f-4ca9-afcc-c3940a2b624a"><con:settings/><con:parameters><con:parameter><con:name>name</con:name><con:value/><con:style>QUERY</con:style><con:default/><con:description xsi:nil="true"/></con:parameter><con:parameter><con:name>email</con:name><con:value/><con:style>QUERY</con:style><con:default/><con:description xsi:nil="true"/></con:parameter></con:parameters><con:method name="Method 1" id="72132bc0-df9f-488e-9657-c3d5c6475e75" method="POST"><con:settings/><con:parameters><con:parameter><con:name/><con:style>QUERY</con:style></con:parameter></con:parameters><con:representation type="REQUEST"><con:mediaType>application/json</con:mediaType><con:params/></con:representation><con:representation type="FAULT"><con:mediaType>application/json</con:mediaType><con:status>404 500</con:status><con:params/><con:element xmlns:user="http://localhost/localhost:8080/users/">user:Fault</con:element></con:representation><con:representation type="RESPONSE"><con:mediaType>application/json</con:mediaType><con:status>200</con:status><con:params/><con:element xmlns:user="http://localhost/localhost:8080/users/">user:Response</con:element></con:representation><con:request name="Alice" id="2ff59136-e99f-48d7-9d10-2f448d55cab1" mediaType="application/json" postQueryString="false"><con:settings><con:setting id="com.eviware.soapui.impl.wsdl.WsdlRequest@request-headers">&lt;xml-fragment/></con:setting></con:settings><con:endpoint>http://localhost:8080</con:endpoint><con:request/><con:originalUri>http://localhost/localhost:8080/users/</con:originalUri><con:credentials><con:authType>No Authorization</con:authType></con:credentials><con:jmsConfig JMSDeliveryMode="PERSISTENT"/><con:jmsPropertyConfig/><con:parameters>
  <con:entry key="name" value="Alice"/>
  <con:entry key="email" value="alice@domain.com"/>
</con:parameters><con:parameterOrder><con:entry>name</con:entry><con:entry>email</con:entry><con:entry/></con:parameterOrder></con:request><con:request name="Bob" id="178d48cd-20a7-4300-af68-861a313a7324" mediaType="application/json" postQueryString="false"><con:settings/><con:endpoint>http://localhost:8080</con:endpoint><con:request/><con:credentials><con:authType>No Authorization</con:authType></con:credentials><con:jmsConfig JMSDeliveryMode="PERSISTENT"/><con:jmsPropertyConfig/><con:parameters>
  <con:entry key="name" value="Bob"/>
  <con:entry key="email" value="bob@domain.com"/>
</con:parameters><con:parameterOrder><con:entry>name</con:entry><con:entry>email</con:entry><con:entry/></con:parameterOrder></con:request><con:request name="Caitlyn" id="178d48cd-20a7-4300-af68-861a313a7324" mediaType="application/json" postQueryString="false"><con:settings><con:setting id="com.eviware.soapui.impl.wsdl.WsdlRequest@request-headers">&lt;xml-fragment/></con:setting></con:settings><con:endpoint>http://localhost:8080</con:endpoint><con:request/><con:originalUri>http://localhost/user/addUser</con:originalUri><con:credentials><con:authType>No Authorization</con:authType></con:credentials><con:jmsConfig JMSDeliveryMode="PERSISTENT"/><con:jmsPropertyConfig/><con:parameters>
  <con:entry key="name" value="Caitlyn"/>
  <con:entry key="email" value="caitlyn@domain.com"/>
</con:parameters><con:parameterOrder><con:entry>name</con:entry><con:entry>email</con:entry><con:entry/></con:parameterOrder></con:request></con:method></con:resource><con:resource name="findAll" path="/user/getAll" id="45d26f2f-3564-49e5-b0eb-cc1eb0faeb38"><con:settings/><con:parameters/><con:method name="Method 1" id="ed5f790d-644a-45c1-9163-c097ef2dbfc3" method="GET"><con:settings/><con:parameters/><con:representation type="FAULT"><con:mediaType>application/json</con:mediaType><con:status>404</con:status><con:params/><con:element xmlns:fin="http://localhost/user/findAll">fin:Fault</con:element></con:representation><con:representation type="RESPONSE"><con:mediaType>application/json</con:mediaType><con:status>200</con:status><con:params/><con:element>Response</con:element></con:representation><con:request name="Request 1" id="06b143e3-c231-4087-b186-85d6c5a4957a" mediaType="application/json"><con:settings><con:setting id="com.eviware.soapui.impl.wsdl.WsdlRequest@request-headers">&lt;xml-fragment/></con:setting></con:settings><con:endpoint>http://localhost:8080</con:endpoint><con:request/><con:originalUri>http://localhost/user/findAll</con:originalUri><con:credentials><con:authType>No Authorization</con:authType></con:credentials><con:jmsConfig JMSDeliveryMode="PERSISTENT"/><con:jmsPropertyConfig/><con:parameters/></con:request></con:method></con:resource></con:interface><con:testSuite id="4ec32d3f-b5cc-4998-a892-e127c3e55bd7" name="Setup"><con:settings/><con:runType>SEQUENTIAL</con:runType><con:testCase id="d10df8cf-9ca4-46d3-8b3b-8f8059b65b08" failOnError="true" failTestCaseOnErrors="true" keepSession="false" maxResults="0" name="Users" searchProperties="true"><con:settings/><con:testStep type="restrequest" name="Method 1 - Alice" id="851a3c4b-509b-42bf-992a-a6b5edaf4856"><con:settings/><con:config service="http://localhost:8080" resourcePath="/user/addUser" methodName="Method 1" xsi:type="con:RestRequestStep" xmlns:xsi="http://www.w3.org/2001/XMLSchema-instance"><con:restRequest name="Method 1 - Alice" id="2ff59136-e99f-48d7-9d10-2f448d55cab1" mediaType="application/json" postQueryString="false"><con:settings><con:setting id="com.eviware.soapui.impl.wsdl.WsdlRequest@request-headers">&lt;xml-fragment/></con:setting></con:settings><con:endpoint>http://localhost:8080</con:endpoint><con:request/><con:originalUri>http://localhost/localhost:8080/users/</con:originalUri><con:credentials><con:authType>No Authorization</con:authType></con:credentials><con:jmsConfig JMSDeliveryMode="PERSISTENT"/><con:jmsPropertyConfig/><con:parameters>
  <con:entry key="name" value="Alice"/>
  <con:entry key="email" value="alice@domain.com"/>
</con:parameters><con:parameterOrder><con:entry>name</con:entry><con:entry>email</con:entry><con:entry/></con:parameterOrder></con:restRequest></con:config></con:testStep><con:testStep type="restrequest" name="Method 1 - Bob" id="f46485a3-1344-475d-b461-081be5834bbc"><con:settings/><con:config service="http://localhost:8080" resourcePath="/user/addUser" methodName="Method 1" xsi:type="con:RestRequestStep" xmlns:xsi="http://www.w3.org/2001/XMLSchema-instance"><con:restRequest name="Method 1 - Bob" id="178d48cd-20a7-4300-af68-861a313a7324" mediaType="application/json" postQueryString="false"><con:settings/><con:endpoint>http://localhost:8080</con:endpoint><con:request/><con:originalUri>http://localhost/user/addUser</con:originalUri><con:credentials><con:authType>No Authorization</con:authType></con:credentials><con:jmsConfig JMSDeliveryMode="PERSISTENT"/><con:jmsPropertyConfig/><con:parameters>
  <con:entry key="name" value="Bob"/>
  <con:entry key="email" value="bob@domain.com"/>
</con:parameters><con:parameterOrder><con:entry>name</con:entry><con:entry>email</con:entry><con:entry/></con:parameterOrder></con:restRequest></con:config></con:testStep><con:testStep type="restrequest" name="Method 1 - Caitlyn" id="0a208899-ef63-4abd-8e1a-17faac6a673d"><con:settings/><con:config service="http://localhost:8080" resourcePath="/user/addUser" methodName="Method 1" xsi:type="con:RestRequestStep" xmlns:xsi="http://www.w3.org/2001/XMLSchema-instance"><con:restRequest name="Method 1 - Caitlyn" id="178d48cd-20a7-4300-af68-861a313a7324" mediaType="application/json" postQueryString="false"><con:settings><con:setting id="com.eviware.soapui.impl.wsdl.WsdlRequest@request-headers">&lt;xml-fragment/></con:setting></con:settings><con:endpoint>http://localhost:8080</con:endpoint><con:request/><con:originalUri>http://localhost/user/addUser</con:originalUri><con:credentials><con:authType>No Authorization</con:authType></con:credentials><con:jmsConfig JMSDeliveryMode="PERSISTENT"/><con:jmsPropertyConfig/><con:parameters>
  <con:entry key="name" value="Caitlyn"/>
  <con:entry key="email" value="caitlyn@domain.com"/>
</con:parameters><con:parameterOrder><con:entry>name</con:entry><con:entry>email</con:entry><con:entry/></con:parameterOrder></con:restRequest></con:config></con:testStep><con:properties/></con:testCase><con:properties/></con:testSuite><con:properties/><con:wssContainer/><con:oAuth2ProfileContainer/><con:oAuth1ProfileContainer/></con:soapui-project>